ai/backend/accelerator/cuda_mock/VERSION
ai/backend/accelerator/cuda_mock/__init__.py
ai/backend/accelerator/cuda_mock/defs.py
ai/backend/accelerator/cuda_mock/plugin.py
ai/backend/accelerator/cuda_mock/py.typed
ai/backend/accelerator/cuda_mock/types.py
backend.ai_accelerator_cuda_mock-23.3.0.dist-info/METADATA
backend.ai_accelerator_cuda_mock-23.3.0.dist-info/WHEEL
backend.ai_accelerator_cuda_mock-23.3.0.dist-info/entry_points.txt
backend.ai_accelerator_cuda_mock-23.3.0.dist-info/namespace_packages.txt
backend.ai_accelerator_cuda_mock-23.3.0.dist-info/top_level.txt
backend.ai_accelerator_cuda_mock-23.3.0.dist-info/RECORD
