Metadata-Version: 2.1
Name: backend.ai-accelerator-cuda-mock
Version: 23.3.0
Summary: Backend.AI Accelerator Plugin for CUDA (Mockup)
Home-page: https://github.com/lablup/backend.ai
Author: Lablup Inc. and contributors
License: LGPLv3
Project-URL: Documentation, https://docs.backend.ai/
Project-URL: Source, https://github.com/lablup/backend.ai
Classifier: Intended Audience :: Developers
Classifier: Operating System :: MacOS :: MacOS X
Classifier: Operating System :: POSIX :: Linux
Classifier: Programming Language :: Python
Classifier: Programming Language :: Python :: 3
Classifier: Environment :: No Input/Output (Daemon)
Classifier: Topic :: Scientific/Engineering
Classifier: Topic :: Software Development
Classifier: Development Status :: 5 - Production/Stable
Classifier: License :: OSI Approved :: GNU Lesser General Public License v3 or later (LGPLv3+)
Requires-Python: >=3.11,<3.12
Requires-Dist: aiodocker (~=0.21.0)
Requires-Dist: backend.ai-agent (==23.03.0)
Requires-Dist: backend.ai-cli (==23.03.0)
Requires-Dist: backend.ai-common (==23.03.0)
Requires-Dist: backend.ai-kernel-binary (==23.03.0)
Requires-Dist: backend.ai-kernel-helper (==23.03.0)
Requires-Dist: backend.ai-kernel (==23.03.0)
Requires-Dist: backend.ai-plugin (==23.03.0)
Requires-Dist: trafaret (~=2.1)
